<?xml version='1.0' encoding='UTF-8'?>
<parameters>
  <formatVersion>2</formatVersion>
  <lastModified revision="61711340399619cdd6d89322db6e90ce228d3d93" time="2026-04-14T18:10:17"/>

  <spheroidVerySimpleTrackLuminosities value="false"/>

  <nodeOperator value="multi">
    <nodeOperator value="satelliteDestructionMassThreshold" >
      <massDestruction           value="1.0"/>
      <massDestructionFractional value="0.0"/>
    </nodeOperator>
  </nodeOperator>

<componentHotHalo value="standard"/></parameters>
