<?xml version="1.0" encoding="UTF-8"?>
<stellarPopulation>
  <description>Metal yield for a Chabrier IMF</description>
  <source>Computed by Galacticus</source>
  <date>Thu Apr 29 13:16:29 (GMT -07:00) 2010</date>
  <ages>
    <description>Age of the stellar population in Gyr</description>
    <data>0.1000E-02</data>
    <data>0.1265E-02</data>
    <data>0.1600E-02</data>
    <data>0.2024E-02</data>
    <data>0.2560E-02</data>
    <data>0.3237E-02</data>
    <data>0.4095E-02</data>
    <data>0.5179E-02</data>
    <data>0.6551E-02</data>
    <data>0.8286E-02</data>
    <data>0.1048E-01</data>
    <data>0.1326E-01</data>
    <data>0.1677E-01</data>
    <data>0.2121E-01</data>
    <data>0.2683E-01</data>
    <data>0.3393E-01</data>
    <data>0.4292E-01</data>
    <data>0.5429E-01</data>
    <data>0.6866E-01</data>
    <data>0.8685E-01</data>
    <data>0.1099E+00</data>
    <data>0.1389E+00</data>
    <data>0.1758E+00</data>
    <data>0.2223E+00</data>
    <data>0.2812E+00</data>
    <data>0.3556E+00</data>
    <data>0.4498E+00</data>
    <data>0.5690E+00</data>
    <data>0.7197E+00</data>
    <data>0.9103E+00</data>
    <data>0.1151E+01</data>
    <data>0.1456E+01</data>
    <data>0.1842E+01</data>
    <data>0.2330E+01</data>
    <data>0.2947E+01</data>
    <data>0.3728E+01</data>
    <data>0.4715E+01</data>
    <data>0.5964E+01</data>
    <data>0.7543E+01</data>
    <data>0.9541E+01</data>
    <data>0.1207E+02</data>
    <data>0.1526E+02</data>
    <data>0.1931E+02</data>
    <data>0.2442E+02</data>
    <data>0.3089E+02</data>
    <data>0.3907E+02</data>
    <data>0.4942E+02</data>
    <data>0.6251E+02</data>
    <data>0.7906E+02</data>
    <data>0.1000E+03</data>
  </ages>
  <metallicities>
    <description>Metallicity (fractional mass of total metals) of the stellar population</description>
    <data>0.0000E+00</data>
    <data>0.1000E-03</data>
    <data>0.2225E-03</data>
    <data>0.4949E-03</data>
    <data>0.1101E-02</data>
    <data>0.2449E-02</data>
    <data>0.5449E-02</data>
    <data>0.1212E-01</data>
    <data>0.2697E-01</data>
    <data>0.6000E-01</data>
  </metallicities>
  <metalYield>
    <data>0.0000E+00</data>
    <data>0.0000E+00</data>
    <data>0.0000E+00</data>
    <data>0.0000E+00</data>
    <data>0.0000E+00</data>
    <data>0.0000E+00</data>
    <data>0.0000E+00</data>
    <data>0.0000E+00</data>
    <data>0.0000E+00</data>
    <data>0.0000E+00</data>
    <data>0.0000E+00</data>
    <data>0.0000E+00</data>
    <data>0.0000E+00</data>
    <data>0.0000E+00</data>
    <data>0.0000E+00</data>
    <data>0.0000E+00</data>
    <data>0.0000E+00</data>
    <data>0.0000E+00</data>
    <data>0.0000E+00</data>
    <data>0.0000E+00</data>
    <data>0.0000E+00</data>
    <data>0.0000E+00</data>
    <data>0.0000E+00</data>
    <data>0.0000E+00</data>
    <data>0.0000E+00</data>
    <data>0.0000E+00</data>
    <data>0.0000E+00</data>
    <data>0.0000E+00</data>
    <data>0.0000E+00</data>
    <data>0.0000E+00</data>
    <data>0.0000E+00</data>
    <data>0.0000E+00</data>
    <data>0.0000E+00</data>
    <data>0.0000E+00</data>
    <data>0.0000E+00</data>
    <data>0.0000E+00</data>
    <data>0.0000E+00</data>
    <data>0.0000E+00</data>
    <data>0.0000E+00</data>
    <data>0.0000E+00</data>
    <data>0.0000E+00</data>
    <data>0.0000E+00</data>
    <data>0.0000E+00</data>
    <data>0.0000E+00</data>
    <data>0.0000E+00</data>
    <data>0.0000E+00</data>
    <data>0.0000E+00</data>
    <data>0.0000E+00</data>
    <data>0.8561E-02</data>
    <data>0.0000E+00</data>
    <data>0.3459E-02</data>
    <data>0.3742E-02</data>
    <data>0.3244E-02</data>
    <data>0.1519E-02</data>
    <data>0.1333E-02</data>
    <data>0.4676E-03</data>
    <data>0.9914E-04</data>
    <data>0.0000E+00</data>
    <data>0.8561E-02</data>
    <data>0.2426E-02</data>
    <data>0.3648E-02</data>
    <data>0.3991E-02</data>
    <data>0.3800E-02</data>
    <data>0.5311E-02</data>
    <data>0.4754E-02</data>
    <data>0.3068E-02</data>
    <data>0.5773E-02</data>
    <data>0.8331E-02</data>
    <data>0.8561E-02</data>
    <data>0.5592E-02</data>
    <data>0.4629E-02</data>
    <data>0.4561E-02</data>
    <data>0.4155E-02</data>
    <data>0.5664E-02</data>
    <data>0.5333E-02</data>
    <data>0.4390E-02</data>
    <data>0.9263E-02</data>
    <data>0.1258E-01</data>
    <data>0.1051E-01</data>
    <data>0.1236E-01</data>
    <data>0.7338E-02</data>
    <data>0.7435E-02</data>
    <data>0.6328E-02</data>
    <data>0.7509E-02</data>
    <data>0.7257E-02</data>
    <data>0.6694E-02</data>
    <data>0.1175E-01</data>
    <data>0.1517E-01</data>
    <data>0.1380E-01</data>
    <data>0.1719E-01</data>
    <data>0.1281E-01</data>
    <data>0.1279E-01</data>
    <data>0.1067E-01</data>
    <data>0.1083E-01</data>
    <data>0.1049E-01</data>
    <data>0.9705E-02</data>
    <data>0.1538E-01</data>
    <data>0.1946E-01</data>
    <data>0.1846E-01</data>
    <data>0.2104E-01</data>
    <data>0.1746E-01</data>
    <data>0.1667E-01</data>
    <data>0.1490E-01</data>
    <data>0.1494E-01</data>
    <data>0.1460E-01</data>
    <data>0.1389E-01</data>
    <data>0.1877E-01</data>
    <data>0.2213E-01</data>
    <data>0.2155E-01</data>
    <data>0.2353E-01</data>
    <data>0.2090E-01</data>
    <data>0.1995E-01</data>
    <data>0.1815E-01</data>
    <data>0.1851E-01</data>
    <data>0.1822E-01</data>
    <data>0.1759E-01</data>
    <data>0.2243E-01</data>
    <data>0.2554E-01</data>
    <data>0.2367E-01</data>
    <data>0.2458E-01</data>
    <data>0.2279E-01</data>
    <data>0.2240E-01</data>
    <data>0.2057E-01</data>
    <data>0.2085E-01</data>
    <data>0.2050E-01</data>
    <data>0.1971E-01</data>
    <data>0.2444E-01</data>
    <data>0.2787E-01</data>
    <data>0.2579E-01</data>
    <data>0.2613E-01</data>
    <data>0.2394E-01</data>
    <data>0.2410E-01</data>
    <data>0.2284E-01</data>
    <data>0.2310E-01</data>
    <data>0.2275E-01</data>
    <data>0.2193E-01</data>
    <data>0.2657E-01</data>
    <data>0.2926E-01</data>
    <data>0.2681E-01</data>
    <data>0.2649E-01</data>
    <data>0.2454E-01</data>
    <data>0.2463E-01</data>
    <data>0.2387E-01</data>
    <data>0.2475E-01</data>
    <data>0.2441E-01</data>
    <data>0.2368E-01</data>
    <data>0.2836E-01</data>
    <data>0.3111E-01</data>
    <data>0.2812E-01</data>
    <data>0.2672E-01</data>
    <data>0.2459E-01</data>
    <data>0.2495E-01</data>
    <data>0.2466E-01</data>
    <data>0.2572E-01</data>
    <data>0.2536E-01</data>
    <data>0.2462E-01</data>
    <data>0.2934E-01</data>
    <data>0.3189E-01</data>
    <data>0.2845E-01</data>
    <data>0.2672E-01</data>
    <data>0.2459E-01</data>
    <data>0.2495E-01</data>
    <data>0.2486E-01</data>
    <data>0.2630E-01</data>
    <data>0.2597E-01</data>
    <data>0.2521E-01</data>
    <data>0.3007E-01</data>
    <data>0.3282E-01</data>
    <data>0.2871E-01</data>
    <data>0.2672E-01</data>
    <data>0.2460E-01</data>
    <data>0.2495E-01</data>
    <data>0.2486E-01</data>
    <data>0.2644E-01</data>
    <data>0.2620E-01</data>
    <data>0.2554E-01</data>
    <data>0.3069E-01</data>
    <data>0.3342E-01</data>
    <data>0.2875E-01</data>
    <data>0.2672E-01</data>
    <data>0.2464E-01</data>
    <data>0.2497E-01</data>
    <data>0.2486E-01</data>
    <data>0.2644E-01</data>
    <data>0.2620E-01</data>
    <data>0.2572E-01</data>
    <data>0.3110E-01</data>
    <data>0.3380E-01</data>
    <data>0.2878E-01</data>
    <data>0.2673E-01</data>
    <data>0.2466E-01</data>
    <data>0.2497E-01</data>
    <data>0.2486E-01</data>
    <data>0.2645E-01</data>
    <data>0.2620E-01</data>
    <data>0.2573E-01</data>
    <data>0.3129E-01</data>
    <data>0.3390E-01</data>
    <data>0.2881E-01</data>
    <data>0.2674E-01</data>
    <data>0.2476E-01</data>
    <data>0.2511E-01</data>
    <data>0.2502E-01</data>
    <data>0.2657E-01</data>
    <data>0.2627E-01</data>
    <data>0.2593E-01</data>
    <data>0.3147E-01</data>
    <data>0.3396E-01</data>
    <data>0.2883E-01</data>
    <data>0.2680E-01</data>
    <data>0.2487E-01</data>
    <data>0.2514E-01</data>
    <data>0.2502E-01</data>
    <data>0.2657E-01</data>
    <data>0.2627E-01</data>
    <data>0.2716E-01</data>
    <data>0.3167E-01</data>
    <data>0.3401E-01</data>
    <data>0.2883E-01</data>
    <data>0.2683E-01</data>
    <data>0.2487E-01</data>
    <data>0.2515E-01</data>
    <data>0.2503E-01</data>
    <data>0.2661E-01</data>
    <data>0.2635E-01</data>
    <data>0.2722E-01</data>
    <data>0.3182E-01</data>
    <data>0.3414E-01</data>
    <data>0.2900E-01</data>
    <data>0.2686E-01</data>
    <data>0.2536E-01</data>
    <data>0.2564E-01</data>
    <data>0.2554E-01</data>
    <data>0.2712E-01</data>
    <data>0.2686E-01</data>
    <data>0.2772E-01</data>
    <data>0.3226E-01</data>
    <data>0.3429E-01</data>
    <data>0.2920E-01</data>
    <data>0.2698E-01</data>
    <data>0.2578E-01</data>
    <data>0.2566E-01</data>
    <data>0.2554E-01</data>
    <data>0.2712E-01</data>
    <data>0.2686E-01</data>
    <data>0.2772E-01</data>
    <data>0.3247E-01</data>
    <data>0.3453E-01</data>
    <data>0.2928E-01</data>
    <data>0.2712E-01</data>
    <data>0.2578E-01</data>
    <data>0.2566E-01</data>
    <data>0.2554E-01</data>
    <data>0.2712E-01</data>
    <data>0.2686E-01</data>
    <data>0.2772E-01</data>
    <data>0.3303E-01</data>
    <data>0.3499E-01</data>
    <data>0.3046E-01</data>
    <data>0.2713E-01</data>
    <data>0.2578E-01</data>
    <data>0.2566E-01</data>
    <data>0.2554E-01</data>
    <data>0.2712E-01</data>
    <data>0.2686E-01</data>
    <data>0.2772E-01</data>
    <data>0.3337E-01</data>
    <data>0.3501E-01</data>
    <data>0.3089E-01</data>
    <data>0.2713E-01</data>
    <data>0.2578E-01</data>
    <data>0.2575E-01</data>
    <data>0.2572E-01</data>
    <data>0.2729E-01</data>
    <data>0.2696E-01</data>
    <data>0.2776E-01</data>
    <data>0.3392E-01</data>
    <data>0.3537E-01</data>
    <data>0.3102E-01</data>
    <data>0.2723E-01</data>
    <data>0.2578E-01</data>
    <data>0.2614E-01</data>
    <data>0.2606E-01</data>
    <data>0.2764E-01</data>
    <data>0.2730E-01</data>
    <data>0.2822E-01</data>
    <data>0.3459E-01</data>
    <data>0.3571E-01</data>
    <data>0.3117E-01</data>
    <data>0.2740E-01</data>
    <data>0.2594E-01</data>
    <data>0.2623E-01</data>
    <data>0.2683E-01</data>
    <data>0.2764E-01</data>
    <data>0.2730E-01</data>
    <data>0.2822E-01</data>
    <data>0.3472E-01</data>
    <data>0.3585E-01</data>
    <data>0.3117E-01</data>
    <data>0.2759E-01</data>
    <data>0.2621E-01</data>
    <data>0.2657E-01</data>
    <data>0.2683E-01</data>
    <data>0.2804E-01</data>
    <data>0.2768E-01</data>
    <data>0.2858E-01</data>
    <data>0.3617E-01</data>
    <data>0.3647E-01</data>
    <data>0.3117E-01</data>
    <data>0.2774E-01</data>
    <data>0.2621E-01</data>
    <data>0.2657E-01</data>
    <data>0.2683E-01</data>
    <data>0.2804E-01</data>
    <data>0.2769E-01</data>
    <data>0.2864E-01</data>
    <data>0.3693E-01</data>
    <data>0.3707E-01</data>
    <data>0.3192E-01</data>
    <data>0.2802E-01</data>
    <data>0.2687E-01</data>
    <data>0.2719E-01</data>
    <data>0.2706E-01</data>
    <data>0.2862E-01</data>
    <data>0.2825E-01</data>
    <data>0.2909E-01</data>
    <data>0.3833E-01</data>
    <data>0.3766E-01</data>
    <data>0.3203E-01</data>
    <data>0.2823E-01</data>
    <data>0.2688E-01</data>
    <data>0.2731E-01</data>
    <data>0.2728E-01</data>
    <data>0.2887E-01</data>
    <data>0.2857E-01</data>
    <data>0.2951E-01</data>
    <data>0.3868E-01</data>
    <data>0.3833E-01</data>
    <data>0.3249E-01</data>
    <data>0.2853E-01</data>
    <data>0.2711E-01</data>
    <data>0.2749E-01</data>
    <data>0.2741E-01</data>
    <data>0.2899E-01</data>
    <data>0.2869E-01</data>
    <data>0.2963E-01</data>
    <data>0.3900E-01</data>
    <data>0.3883E-01</data>
    <data>0.3279E-01</data>
    <data>0.2876E-01</data>
    <data>0.2722E-01</data>
    <data>0.2760E-01</data>
    <data>0.2750E-01</data>
    <data>0.2909E-01</data>
    <data>0.2880E-01</data>
    <data>0.2975E-01</data>
    <data>0.3915E-01</data>
    <data>0.3888E-01</data>
    <data>0.3291E-01</data>
    <data>0.2916E-01</data>
    <data>0.2736E-01</data>
    <data>0.2772E-01</data>
    <data>0.2762E-01</data>
    <data>0.2921E-01</data>
    <data>0.2891E-01</data>
    <data>0.2987E-01</data>
    <data>0.3928E-01</data>
    <data>0.3916E-01</data>
    <data>0.3310E-01</data>
    <data>0.2933E-01</data>
    <data>0.2748E-01</data>
    <data>0.2784E-01</data>
    <data>0.2774E-01</data>
    <data>0.2933E-01</data>
    <data>0.2903E-01</data>
    <data>0.2999E-01</data>
    <data>0.3941E-01</data>
    <data>0.3932E-01</data>
    <data>0.3334E-01</data>
    <data>0.2946E-01</data>
    <data>0.2755E-01</data>
    <data>0.2791E-01</data>
    <data>0.2781E-01</data>
    <data>0.2939E-01</data>
    <data>0.2908E-01</data>
    <data>0.3003E-01</data>
    <data>0.3946E-01</data>
    <data>0.3934E-01</data>
    <data>0.3334E-01</data>
    <data>0.2954E-01</data>
    <data>0.2762E-01</data>
    <data>0.2796E-01</data>
    <data>0.2785E-01</data>
    <data>0.2944E-01</data>
    <data>0.2914E-01</data>
    <data>0.3010E-01</data>
    <data>0.3951E-01</data>
    <data>0.3940E-01</data>
    <data>0.3339E-01</data>
    <data>0.2959E-01</data>
    <data>0.2766E-01</data>
    <data>0.2802E-01</data>
    <data>0.2792E-01</data>
    <data>0.2951E-01</data>
    <data>0.2920E-01</data>
    <data>0.3016E-01</data>
    <data>0.3959E-01</data>
    <data>0.3950E-01</data>
    <data>0.3349E-01</data>
    <data>0.2965E-01</data>
    <data>0.2770E-01</data>
    <data>0.2805E-01</data>
    <data>0.2794E-01</data>
    <data>0.2952E-01</data>
    <data>0.2921E-01</data>
    <data>0.3018E-01</data>
    <data>0.3959E-01</data>
    <data>0.3950E-01</data>
    <data>0.3350E-01</data>
    <data>0.2968E-01</data>
    <data>0.2772E-01</data>
    <data>0.2808E-01</data>
    <data>0.2798E-01</data>
    <data>0.2957E-01</data>
    <data>0.2926E-01</data>
    <data>0.3021E-01</data>
    <data>0.3965E-01</data>
    <data>0.3951E-01</data>
    <data>0.3356E-01</data>
    <data>0.2972E-01</data>
    <data>0.2775E-01</data>
    <data>0.2810E-01</data>
    <data>0.2799E-01</data>
    <data>0.2957E-01</data>
    <data>0.2927E-01</data>
    <data>0.3023E-01</data>
    <data>0.3966E-01</data>
    <data>0.3956E-01</data>
    <data>0.3359E-01</data>
    <data>0.2977E-01</data>
    <data>0.2776E-01</data>
    <data>0.2813E-01</data>
    <data>0.2803E-01</data>
    <data>0.2961E-01</data>
    <data>0.2931E-01</data>
    <data>0.3027E-01</data>
    <data>0.3967E-01</data>
    <data>0.3958E-01</data>
    <data>0.3361E-01</data>
    <data>0.2981E-01</data>
    <data>0.2776E-01</data>
    <data>0.2813E-01</data>
    <data>0.2803E-01</data>
    <data>0.2961E-01</data>
    <data>0.2931E-01</data>
    <data>0.3027E-01</data>
    <data>0.3969E-01</data>
    <data>0.3961E-01</data>
    <data>0.3366E-01</data>
    <data>0.2983E-01</data>
    <data>0.2776E-01</data>
    <data>0.2813E-01</data>
    <data>0.2803E-01</data>
    <data>0.2961E-01</data>
    <data>0.2932E-01</data>
    <data>0.3028E-01</data>
    <data>0.3971E-01</data>
    <data>0.3962E-01</data>
    <data>0.3367E-01</data>
    <data>0.2983E-01</data>
    <data>0.2776E-01</data>
    <data>0.2813E-01</data>
    <data>0.2803E-01</data>
    <data>0.2962E-01</data>
    <data>0.2932E-01</data>
    <data>0.3028E-01</data>
    <data>0.3972E-01</data>
    <data>0.3964E-01</data>
    <data>0.3369E-01</data>
    <data>0.2986E-01</data>
    <data>0.2777E-01</data>
    <data>0.2814E-01</data>
    <data>0.2804E-01</data>
    <data>0.2962E-01</data>
    <data>0.2933E-01</data>
    <data>0.3029E-01</data>
    <data>0.3973E-01</data>
    <data>0.3965E-01</data>
    <data>0.3369E-01</data>
    <data>0.2986E-01</data>
    <data>0.2778E-01</data>
    <data>0.2814E-01</data>
    <data>0.2804E-01</data>
    <data>0.2963E-01</data>
    <data>0.2933E-01</data>
    <data>0.3029E-01</data>
    <data>0.3973E-01</data>
    <data>0.3965E-01</data>
    <data>0.3370E-01</data>
    <data>0.2988E-01</data>
  </metalYield>
</stellarPopulation>
