<filter>
  <description>LSST_u</description>
  <name>LSST_u</name>
  <origin>throughputs_1.2</origin>
  <response>
    <datum>   3103.0   0.000116807403265</datum>
    <datum>   3104.0   0.000134629885043</datum>
    <datum>   3105.0   0.000152939681333</datum>
    <datum>   3106.0   0.000171741322244</datum>
    <datum>   3107.0   0.000191039343649</datum>
    <datum>   3108.0   0.000210838287186</datum>
    <datum>   3109.0   0.000231142700264</datum>
    <datum>   3110.0   0.000251957136064</datum>
    <datum>   3111.0   0.000264605224412</datum>
    <datum>   3112.0   0.000277580074075</datum>
    <datum>   3113.0   0.000290884652423</datum>
    <datum>   3114.0   0.000304521929375</datum>
    <datum>   3115.0   0.000318494877405</datum>
    <datum>   3116.0   0.000332806471537</datum>
    <datum>   3117.0   0.000347459689352</datum>
    <datum>   3118.0   0.000362457510984</datum>
    <datum>   3119.0   0.000377802919123</datum>
    <datum>   3120.0   0.000393498899018</datum>
    <datum>   3121.0   0.000458629205662</datum>
    <datum>   3122.0   0.000525741281856</datum>
    <datum>   3123.0   0.000594853764335</datum>
    <datum>   3124.0   0.000665985306709</datum>
    <datum>   3125.0   0.000739154579463</datum>
    <datum>   3126.0   0.000814380269968</datum>
    <datum>   3127.0   0.000891681082489</datum>
    <datum>   3128.0   0.000971075738185</datum>
    <datum>   3129.0   0.00105258297512</datum>
    <datum>   3130.0   0.00113622154828</datum>
    <datum>   3131.0   0.00119251719821</datum>
    <datum>   3132.0   0.001249902195</datum>
    <datum>   3133.0   0.00130838530498</datum>
    <datum>   3134.0   0.0013679753066</datum>
    <datum>   3135.0   0.00142868099042</datum>
    <datum>   3136.0   0.00149051115917</datum>
    <datum>   3137.0   0.00155347462766</datum>
    <datum>   3138.0   0.0016175802229</datum>
    <datum>   3139.0   0.00168283678403</datum>
    <datum>   3140.0   0.00174925316237</datum>
    <datum>   3141.0   0.00187593813883</datum>
    <datum>   3142.0   0.00200634318329</datum>
    <datum>   3143.0   0.00214051152333</datum>
    <datum>   3144.0   0.00227848642747</datum>
    <datum>   3145.0   0.00242031120519</datum>
    <datum>   3146.0   0.00256602920694</datum>
    <datum>   3147.0   0.00271568382417</datum>
    <datum>   3148.0   0.00286931848931</datum>
    <datum>   3149.0   0.00302697667583</datum>
    <datum>   3150.0   0.00318870189825</datum>
    <datum>   3151.0   0.00367965836662</datum>
    <datum>   3152.0   0.00417845746332</datum>
    <datum>   3153.0   0.00468514878391</datum>
    <datum>   3154.0   0.00519978196916</datum>
    <datum>   3155.0   0.00572240670512</datum>
    <datum>   3156.0   0.00625307272312</datum>
    <datum>   3157.0   0.00679182979974</datum>
    <datum>   3158.0   0.00733872775691</datum>
    <datum>   3159.0   0.00789381646185</datum>
    <datum>   3160.0   0.00845714582717</datum>
    <datum>   3161.0   0.0101720080602</datum>
    <datum>   3162.0   0.0119270786528</datum>
    <datum>   3163.0   0.013722662571</datum>
    <datum>   3164.0   0.015559065056</datum>
    <datum>   3165.0   0.0174365916242</datum>
    <datum>   3166.0   0.0193555480674</datum>
    <datum>   3167.0   0.0213162404526</datum>
    <datum>   3168.0   0.0233189751226</datum>
    <datum>   3169.0   0.0253640586956</datum>
    <datum>   3170.0   0.0274517980657</datum>
    <datum>   3171.0   0.0293735550797</datum>
    <datum>   3172.0   0.0313214605316</datum>
    <datum>   3173.0   0.0332956670981</datum>
    <datum>   3174.0   0.0352963276556</datum>
    <datum>   3175.0   0.0373235952797</datum>
    <datum>   3176.0   0.0393776232455</datum>
    <datum>   3177.0   0.0414585650281</datum>
    <datum>   3178.0   0.0435665743022</datum>
    <datum>   3179.0   0.0457018049427</datum>
    <datum>   3180.0   0.0478644110245</datum>
    <datum>   3181.0   0.0493961803938</datum>
    <datum>   3182.0   0.050954863176</datum>
    <datum>   3183.0   0.0525406398411</datum>
    <datum>   3184.0   0.054153691005</datum>
    <datum>   3185.0   0.0557941974291</datum>
    <datum>   3186.0   0.0574623400211</datum>
    <datum>   3187.0   0.0591582998342</datum>
    <datum>   3188.0   0.0608822580679</datum>
    <datum>   3189.0   0.0626343960674</datum>
    <datum>   3190.0   0.0644148953241</datum>
    <datum>   3191.0   0.0646736774658</datum>
    <datum>   3192.0   0.0649319134013</datum>
    <datum>   3193.0   0.0651896031371</datum>
    <datum>   3194.0   0.0654467466801</datum>
    <datum>   3195.0   0.065703344037</datum>
    <datum>   3196.0   0.0659593952152</datum>
    <datum>   3197.0   0.0662149002219</datum>
    <datum>   3198.0   0.0664698590648</datum>
    <datum>   3199.0   0.0667242717516</datum>
    <datum>   3200.0   0.0669781382902</datum>
    <datum>   3201.0   0.0681387008957</datum>
    <datum>   3202.0   0.0693105934388</datum>
    <datum>   3203.0   0.070493868403</datum>
    <datum>   3204.0   0.0716885783304</datum>
    <datum>   3205.0   0.0728947758219</datum>
    <datum>   3206.0   0.0741125135368</datum>
    <datum>   3207.0   0.0753418441934</datum>
    <datum>   3208.0   0.0765828205688</datum>
    <datum>   3209.0   0.0778354954989</datum>
    <datum>   3210.0   0.0790999218783</datum>
    <datum>   3211.0   0.080672101024</datum>
    <datum>   3212.0   0.0822501530797</datum>
    <datum>   3213.0   0.083834075174</datum>
    <datum>   3214.0   0.0854238644327</datum>
    <datum>   3215.0   0.0870195179783</datum>
    <datum>   3216.0   0.0886210329303</datum>
    <datum>   3217.0   0.0902284064052</datum>
    <datum>   3218.0   0.0918416355164</datum>
    <datum>   3219.0   0.0934607173742</datum>
    <datum>   3220.0   0.0950856490861</datum>
    <datum>   3221.0   0.099006875813</datum>
    <datum>   3222.0   0.102966901561</datum>
    <datum>   3223.0   0.106965882084</datum>
    <datum>   3224.0   0.111003973215</datum>
    <datum>   3225.0   0.115081330873</datum>
    <datum>   3226.0   0.119198111056</datum>
    <datum>   3227.0   0.123354469845</datum>
    <datum>   3228.0   0.127550563402</datum>
    <datum>   3229.0   0.131786547974</datum>
    <datum>   3230.0   0.136062579886</datum>
    <datum>   3231.0   0.140252812329</datum>
    <datum>   3232.0   0.144504595354</datum>
    <datum>   3233.0   0.148818238259</datum>
    <datum>   3234.0   0.153194050623</datum>
    <datum>   3235.0   0.15763234231</datum>
    <datum>   3236.0   0.162133423469</datum>
    <datum>   3237.0   0.166697604532</datum>
    <datum>   3238.0   0.171325196219</datum>
    <datum>   3239.0   0.176016509531</datum>
    <datum>   3240.0   0.180771855756</datum>
    <datum>   3241.0   0.18145784565</datum>
    <datum>   3242.0   0.182141543892</datum>
    <datum>   3243.0   0.182822921995</datum>
    <datum>   3244.0   0.183501951465</datum>
    <datum>   3245.0   0.184178603795</datum>
    <datum>   3246.0   0.184852850471</datum>
    <datum>   3247.0   0.185524662967</datum>
    <datum>   3248.0   0.186194012745</datum>
    <datum>   3249.0   0.186860871259</datum>
    <datum>   3250.0   0.187525209952</datum>
    <datum>   3251.0   0.188244521635</datum>
    <datum>   3252.0   0.188958706786</datum>
    <datum>   3253.0   0.189667734347</datum>
    <datum>   3254.0   0.190371573236</datum>
    <datum>   3255.0   0.191070192347</datum>
    <datum>   3256.0   0.191763560552</datum>
    <datum>   3257.0   0.192451646699</datum>
    <datum>   3258.0   0.193134419612</datum>
    <datum>   3259.0   0.19381184809</datum>
    <datum>   3260.0   0.194483900912</datum>
    <datum>   3261.0   0.195629166132</datum>
    <datum>   3262.0   0.196778184843</datum>
    <datum>   3263.0   0.197930962812</datum>
    <datum>   3264.0   0.199087505806</datum>
    <datum>   3265.0   0.200247819592</datum>
    <datum>   3266.0   0.201411909938</datum>
    <datum>   3267.0   0.202579782615</datum>
    <datum>   3268.0   0.203751443394</datum>
    <datum>   3269.0   0.204926898045</datum>
    <datum>   3270.0   0.206106152341</datum>
    <datum>   3271.0   0.206642329779</datum>
    <datum>   3272.0   0.207176710169</datum>
    <datum>   3273.0   0.207709284541</datum>
    <datum>   3274.0   0.208240043923</datum>
    <datum>   3275.0   0.208768979343</datum>
    <datum>   3276.0   0.209296081828</datum>
    <datum>   3277.0   0.209821342403</datum>
    <datum>   3278.0   0.210344752096</datum>
    <datum>   3279.0   0.21086630193</datum>
    <datum>   3280.0   0.211385982929</datum>
    <datum>   3281.0   0.212941670991</datum>
    <datum>   3282.0   0.214501891287</datum>
    <datum>   3283.0   0.216066649788</datum>
    <datum>   3284.0   0.217635952465</datum>
    <datum>   3285.0   0.219209805295</datum>
    <datum>   3286.0   0.220788214256</datum>
    <datum>   3287.0   0.222371185328</datum>
    <datum>   3288.0   0.223958724493</datum>
    <datum>   3289.0   0.225550837738</datum>
    <datum>   3290.0   0.227147531051</datum>
    <datum>   3291.0   0.228021971766</datum>
    <datum>   3292.0   0.228897966543</datum>
    <datum>   3293.0   0.229775514802</datum>
    <datum>   3294.0   0.230654615963</datum>
    <datum>   3295.0   0.231535269449</datum>
    <datum>   3296.0   0.23241747468</datum>
    <datum>   3297.0   0.233301231077</datum>
    <datum>   3298.0   0.234186538061</datum>
    <datum>   3299.0   0.235073395053</datum>
    <datum>   3300.0   0.235961801475</datum>
    <datum>   3301.0   0.235859976548</datum>
    <datum>   3302.0   0.235757810876</datum>
    <datum>   3303.0   0.23565530435</datum>
    <datum>   3304.0   0.235552456859</datum>
    <datum>   3305.0   0.235449268296</datum>
    <datum>   3306.0   0.23534573855</datum>
    <datum>   3307.0   0.235241867512</datum>
    <datum>   3308.0   0.235137655073</datum>
    <datum>   3309.0   0.235033101124</datum>
    <datum>   3310.0   0.234928205555</datum>
    <datum>   3311.0   0.235913092233</datum>
    <datum>   3312.0   0.236898886921</datum>
    <datum>   3313.0   0.23788558972</datum>
    <datum>   3314.0   0.238873200733</datum>
    <datum>   3315.0   0.239861720062</datum>
    <datum>   3316.0   0.240851147809</datum>
    <datum>   3317.0   0.241841484076</datum>
    <datum>   3318.0   0.242832728966</datum>
    <datum>   3319.0   0.24382488258</datum>
    <datum>   3320.0   0.244817945021</datum>
    <datum>   3321.0   0.245279620676</datum>
    <datum>   3322.0   0.245741345379</datum>
    <datum>   3323.0   0.246203118911</datum>
    <datum>   3324.0   0.246664941052</datum>
    <datum>   3325.0   0.247126811584</datum>
    <datum>   3326.0   0.247588730288</datum>
    <datum>   3327.0   0.248050696944</datum>
    <datum>   3328.0   0.248512711335</datum>
    <datum>   3329.0   0.24897477324</datum>
    <datum>   3330.0   0.249436882443</datum>
    <datum>   3331.0   0.249305334756</datum>
    <datum>   3332.0   0.24917376399</datum>
    <datum>   3333.0   0.249042170212</datum>
    <datum>   3334.0   0.248910553488</datum>
    <datum>   3335.0   0.248778913886</datum>
    <datum>   3336.0   0.248647251472</datum>
    <datum>   3337.0   0.248515566312</datum>
    <datum>   3338.0   0.248383858473</datum>
    <datum>   3339.0   0.248252128022</datum>
    <datum>   3340.0   0.248120375025</datum>
    <datum>   3341.0   0.249102587358</datum>
    <datum>   3342.0   0.250086264062</datum>
    <datum>   3343.0   0.251071404776</datum>
    <datum>   3344.0   0.252058009142</datum>
    <datum>   3345.0   0.253046076799</datum>
    <datum>   3346.0   0.25403560739</datum>
    <datum>   3347.0   0.255026600553</datum>
    <datum>   3348.0   0.25601905593</datum>
    <datum>   3349.0   0.257012973161</datum>
    <datum>   3350.0   0.258008351885</datum>
    <datum>   3351.0   0.258320815399</datum>
    <datum>   3352.0   0.258633176323</datum>
    <datum>   3353.0   0.258945434672</datum>
    <datum>   3354.0   0.259257590456</datum>
    <datum>   3355.0   0.25956964369</datum>
    <datum>   3356.0   0.259881594385</datum>
    <datum>   3357.0   0.260193442555</datum>
    <datum>   3358.0   0.260505188212</datum>
    <datum>   3359.0   0.260816831368</datum>
    <datum>   3360.0   0.261128372037</datum>
    <datum>   3361.0   0.260993587784</datum>
    <datum>   3362.0   0.260858838694</datum>
    <datum>   3363.0   0.260724124765</datum>
    <datum>   3364.0   0.260589445995</datum>
    <datum>   3365.0   0.260454802385</datum>
    <datum>   3366.0   0.260320193931</datum>
    <datum>   3367.0   0.260185620632</datum>
    <datum>   3368.0   0.260051082488</datum>
    <datum>   3369.0   0.259916579496</datum>
    <datum>   3370.0   0.259782111655</datum>
    <datum>   3371.0   0.260094167618</datum>
    <datum>   3372.0   0.260406135199</datum>
    <datum>   3373.0   0.260718014364</datum>
    <datum>   3374.0   0.261029805075</datum>
    <datum>   3375.0   0.261341507298</datum>
    <datum>   3376.0   0.261653120996</datum>
    <datum>   3377.0   0.261964646132</datum>
    <datum>   3378.0   0.262276082673</datum>
    <datum>   3379.0   0.26258743058</datum>
    <datum>   3380.0   0.262898689819</datum>
    <datum>   3381.0   0.263323522841</datum>
    <datum>   3382.0   0.263748120681</datum>
    <datum>   3383.0   0.26417248331</datum>
    <datum>   3384.0   0.264596610701</datum>
    <datum>   3385.0   0.265020502826</datum>
    <datum>   3386.0   0.265444159657</datum>
    <datum>   3387.0   0.265867581168</datum>
    <datum>   3388.0   0.266290767331</datum>
    <datum>   3389.0   0.266713718118</datum>
    <datum>   3390.0   0.267136433502</datum>
    <datum>   3391.0   0.267342469987</datum>
    <datum>   3392.0   0.267548584354</datum>
    <datum>   3393.0   0.26775477659</datum>
    <datum>   3394.0   0.267961046678</datum>
    <datum>   3395.0   0.268167394605</datum>
    <datum>   3396.0   0.268373820354</datum>
    <datum>   3397.0   0.26858032391</datum>
    <datum>   3398.0   0.268786905259</datum>
    <datum>   3399.0   0.268993564385</datum>
    <datum>   3400.0   0.269200301272</datum>
    <datum>   3401.0   0.269409492894</datum>
    <datum>   3402.0   0.269618471142</datum>
    <datum>   3403.0   0.269827235745</datum>
    <datum>   3404.0   0.270035786433</datum>
    <datum>   3405.0   0.270244122934</datum>
    <datum>   3406.0   0.270452244977</datum>
    <datum>   3407.0   0.270660152291</datum>
    <datum>   3408.0   0.270867844605</datum>
    <datum>   3409.0   0.271075321649</datum>
    <datum>   3410.0   0.271282583152</datum>
    <datum>   3411.0   0.271505878696</datum>
    <datum>   3412.0   0.271728804863</datum>
    <datum>   3413.0   0.271951361518</datum>
    <datum>   3414.0   0.272173548523</datum>
    <datum>   3415.0   0.272395365743</datum>
    <datum>   3416.0   0.27261681304</datum>
    <datum>   3417.0   0.272837890278</datum>
    <datum>   3418.0   0.273058597322</datum>
    <datum>   3419.0   0.273278934035</datum>
    <datum>   3420.0   0.273498900282</datum>
    <datum>   3421.0   0.273491583427</datum>
    <datum>   3422.0   0.273484034879</datum>
    <datum>   3423.0   0.273476254744</datum>
    <datum>   3424.0   0.27346824313</datum>
    <datum>   3425.0   0.273460000143</datum>
    <datum>   3426.0   0.273451525892</datum>
    <datum>   3427.0   0.273442820482</datum>
    <datum>   3428.0   0.273433884021</datum>
    <datum>   3429.0   0.273424716617</datum>
    <datum>   3430.0   0.273415318375</datum>
    <datum>   3431.0   0.273198096448</datum>
    <datum>   3432.0   0.272980903198</datum>
    <datum>   3433.0   0.272763738709</datum>
    <datum>   3434.0   0.272546603064</datum>
    <datum>   3435.0   0.272329496347</datum>
    <datum>   3436.0   0.272112418642</datum>
    <datum>   3437.0   0.271895370031</datum>
    <datum>   3438.0   0.271678350599</datum>
    <datum>   3439.0   0.271461360429</datum>
    <datum>   3440.0   0.271244399603</datum>
    <datum>   3441.0   0.271317225047</datum>
    <datum>   3442.0   0.271389685015</datum>
    <datum>   3443.0   0.271461779742</datum>
    <datum>   3444.0   0.271533509467</datum>
    <datum>   3445.0   0.271604874426</datum>
    <datum>   3446.0   0.271675874856</datum>
    <datum>   3447.0   0.271746510994</datum>
    <datum>   3448.0   0.271816783077</datum>
    <datum>   3449.0   0.271886691342</datum>
    <datum>   3450.0   0.271956236025</datum>
    <datum>   3451.0   0.271847339573</datum>
    <datum>   3452.0   0.271738004766</datum>
    <datum>   3453.0   0.271628232418</datum>
    <datum>   3454.0   0.271518023343</datum>
    <datum>   3455.0   0.271407378354</datum>
    <datum>   3456.0   0.271296298266</datum>
    <datum>   3457.0   0.27118478389</datum>
    <datum>   3458.0   0.27107283604</datum>
    <datum>   3459.0   0.270960455526</datum>
    <datum>   3460.0   0.270847643162</datum>
    <datum>   3461.0   0.270731871014</datum>
    <datum>   3462.0   0.27061583391</datum>
    <datum>   3463.0   0.270499532231</datum>
    <datum>   3464.0   0.270382966359</datum>
    <datum>   3465.0   0.270266136673</datum>
    <datum>   3466.0   0.270149043555</datum>
    <datum>   3467.0   0.270031687384</datum>
    <datum>   3468.0   0.26991406854</datum>
    <datum>   3469.0   0.269796187404</datum>
    <datum>   3470.0   0.269678044356</datum>
    <datum>   3471.0   0.269640401274</datum>
    <datum>   3472.0   0.26960250317</datum>
    <datum>   3473.0   0.269564350097</datum>
    <datum>   3474.0   0.269525942105</datum>
    <datum>   3475.0   0.269487279249</datum>
    <datum>   3476.0   0.269448361581</datum>
    <datum>   3477.0   0.269409189152</datum>
    <datum>   3478.0   0.269369762016</datum>
    <datum>   3479.0   0.269330080225</datum>
    <datum>   3480.0   0.269290143832</datum>
    <datum>   3481.0   0.269392707674</datum>
    <datum>   3482.0   0.269494943257</datum>
    <datum>   3483.0   0.269596850299</datum>
    <datum>   3484.0   0.269698428517</datum>
    <datum>   3485.0   0.26979967763</datum>
    <datum>   3486.0   0.269900597358</datum>
    <datum>   3487.0   0.270001187417</datum>
    <datum>   3488.0   0.270101447528</datum>
    <datum>   3489.0   0.27020137741</datum>
    <datum>   3490.0   0.270300976782</datum>
    <datum>   3491.0   0.27052812803</datum>
    <datum>   3492.0   0.270755166127</datum>
    <datum>   3493.0   0.27098209072</datum>
    <datum>   3494.0   0.271208901453</datum>
    <datum>   3495.0   0.271435597973</datum>
    <datum>   3496.0   0.271662179925</datum>
    <datum>   3497.0   0.271888646956</datum>
    <datum>   3498.0   0.272114998712</datum>
    <datum>   3499.0   0.272341234837</datum>
    <datum>   3500.0   0.272567354978</datum>
    <datum>   3501.0   0.272592341984</datum>
    <datum>   3502.0   0.272616877729</datum>
    <datum>   3503.0   0.2726409618</datum>
    <datum>   3504.0   0.272664593786</datum>
    <datum>   3505.0   0.272687773278</datum>
    <datum>   3506.0   0.272710499864</datum>
    <datum>   3507.0   0.272732773134</datum>
    <datum>   3508.0   0.272754592678</datum>
    <datum>   3509.0   0.272775958087</datum>
    <datum>   3510.0   0.272796868951</datum>
    <datum>   3511.0   0.272747062786</datum>
    <datum>   3512.0   0.272696891766</datum>
    <datum>   3513.0   0.272646355709</datum>
    <datum>   3514.0   0.272595454436</datum>
    <datum>   3515.0   0.272544187767</datum>
    <datum>   3516.0   0.272492555522</datum>
    <datum>   3517.0   0.272440557521</datum>
    <datum>   3518.0   0.272388193585</datum>
    <datum>   3519.0   0.272335463535</datum>
    <datum>   3520.0   0.272282367189</datum>
    <datum>   3521.0   0.27219107908</datum>
    <datum>   3522.0   0.272099415129</datum>
    <datum>   3523.0   0.272007375486</datum>
    <datum>   3524.0   0.2719149603</datum>
    <datum>   3525.0   0.271822169722</datum>
    <datum>   3526.0   0.271729003901</datum>
    <datum>   3527.0   0.271635462986</datum>
    <datum>   3528.0   0.271541547126</datum>
    <datum>   3529.0   0.271447256472</datum>
    <datum>   3530.0   0.271352591172</datum>
    <datum>   3531.0   0.271143761717</datum>
    <datum>   3532.0   0.270934709692</datum>
    <datum>   3533.0   0.270725435501</datum>
    <datum>   3534.0   0.270515939548</datum>
    <datum>   3535.0   0.270306222237</datum>
    <datum>   3536.0   0.270096283971</datum>
    <datum>   3537.0   0.269886125155</datum>
    <datum>   3538.0   0.26967574619</datum>
    <datum>   3539.0   0.269465147482</datum>
    <datum>   3540.0   0.269254329433</datum>
    <datum>   3541.0   0.269077520875</datum>
    <datum>   3542.0   0.268900475363</datum>
    <datum>   3543.0   0.268723193277</datum>
    <datum>   3544.0   0.268545675</datum>
    <datum>   3545.0   0.268367920914</datum>
    <datum>   3546.0   0.2681899314</datum>
    <datum>   3547.0   0.26801170684</datum>
    <datum>   3548.0   0.267833247616</datum>
    <datum>   3549.0   0.267654554111</datum>
    <datum>   3550.0   0.267475626706</datum>
    <datum>   3551.0   0.267238870466</datum>
    <datum>   3552.0   0.267001915186</datum>
    <datum>   3553.0   0.266764761372</datum>
    <datum>   3554.0   0.266527409531</datum>
    <datum>   3555.0   0.266289860169</datum>
    <datum>   3556.0   0.266052113793</datum>
    <datum>   3557.0   0.265814170907</datum>
    <datum>   3558.0   0.265576032019</datum>
    <datum>   3559.0   0.265337697634</datum>
    <datum>   3560.0   0.265099168258</datum>
    <datum>   3561.0   0.2649013996</datum>
    <datum>   3562.0   0.26470344819</datum>
    <datum>   3563.0   0.264505314308</datum>
    <datum>   3564.0   0.264306998233</datum>
    <datum>   3565.0   0.264108500246</datum>
    <datum>   3566.0   0.263909820625</datum>
    <datum>   3567.0   0.263710959651</datum>
    <datum>   3568.0   0.263511917603</datum>
    <datum>   3569.0   0.263312694762</datum>
    <datum>   3570.0   0.263113291406</datum>
    <datum>   3571.0   0.263015312745</datum>
    <datum>   3572.0   0.262917057801</datum>
    <datum>   3573.0   0.26281852665</datum>
    <datum>   3574.0   0.262719719368</datum>
    <datum>   3575.0   0.262620636032</datum>
    <datum>   3576.0   0.262521276716</datum>
    <datum>   3577.0   0.262421641497</datum>
    <datum>   3578.0   0.262321730452</datum>
    <datum>   3579.0   0.262221543656</datum>
    <datum>   3580.0   0.262121081185</datum>
    <datum>   3581.0   0.262132666798</datum>
    <datum>   3582.0   0.262143942337</datum>
    <datum>   3583.0   0.262154907537</datum>
    <datum>   3584.0   0.26216556213</datum>
    <datum>   3585.0   0.262175905848</datum>
    <datum>   3586.0   0.262185938426</datum>
    <datum>   3587.0   0.262195659595</datum>
    <datum>   3588.0   0.26220506909</datum>
    <datum>   3589.0   0.262214166641</datum>
    <datum>   3590.0   0.262222951983</datum>
    <datum>   3591.0   0.262256396146</datum>
    <datum>   3592.0   0.262289565974</datum>
    <datum>   3593.0   0.262322461218</datum>
    <datum>   3594.0   0.262355081627</datum>
    <datum>   3595.0   0.262387426951</datum>
    <datum>   3596.0   0.262419496939</datum>
    <datum>   3597.0   0.262451291341</datum>
    <datum>   3598.0   0.262482809907</datum>
    <datum>   3599.0   0.262514052386</datum>
    <datum>   3600.0   0.262545018528</datum>
    <datum>   3601.0   0.262656716512</datum>
    <datum>   3602.0   0.262768256508</datum>
    <datum>   3603.0   0.262879638311</datum>
    <datum>   3604.0   0.262990861713</datum>
    <datum>   3605.0   0.263101926507</datum>
    <datum>   3606.0   0.263212832486</datum>
    <datum>   3607.0   0.263323579441</datum>
    <datum>   3608.0   0.263434167168</datum>
    <datum>   3609.0   0.263544595457</datum>
    <datum>   3610.0   0.263654864101</datum>
    <datum>   3611.0   0.263758662032</datum>
    <datum>   3612.0   0.263862299701</datum>
    <datum>   3613.0   0.263965776913</datum>
    <datum>   3614.0   0.264069093478</datum>
    <datum>   3615.0   0.264172249201</datum>
    <datum>   3616.0   0.264275243892</datum>
    <datum>   3617.0   0.264378077357</datum>
    <datum>   3618.0   0.264480749403</datum>
    <datum>   3619.0   0.264583259838</datum>
    <datum>   3620.0   0.26468560847</datum>
    <datum>   3621.0   0.264786579594</datum>
    <datum>   3622.0   0.264887409919</datum>
    <datum>   3623.0   0.26498809926</datum>
    <datum>   3624.0   0.26508864743</datum>
    <datum>   3625.0   0.265189054242</datum>
    <datum>   3626.0   0.26528931951</datum>
    <datum>   3627.0   0.265389443047</datum>
    <datum>   3628.0   0.265489424667</datum>
    <datum>   3629.0   0.265589264183</datum>
    <datum>   3630.0   0.265688961407</datum>
    <datum>   3631.0   0.26570525108</datum>
    <datum>   3632.0   0.265721382216</datum>
    <datum>   3633.0   0.265737354774</datum>
    <datum>   3634.0   0.265753168716</datum>
    <datum>   3635.0   0.265768824001</datum>
    <datum>   3636.0   0.265784320591</datum>
    <datum>   3637.0   0.265799658444</datum>
    <datum>   3638.0   0.265814837522</datum>
    <datum>   3639.0   0.265829857784</datum>
    <datum>   3640.0   0.265844719191</datum>
    <datum>   3641.0   0.265827343057</datum>
    <datum>   3642.0   0.265809796931</datum>
    <datum>   3643.0   0.26579208079</datum>
    <datum>   3644.0   0.265774194609</datum>
    <datum>   3645.0   0.265756138363</datum>
    <datum>   3646.0   0.26573791203</datum>
    <datum>   3647.0   0.265719515583</datum>
    <datum>   3648.0   0.265700949</datum>
    <datum>   3649.0   0.265682212256</datum>
    <datum>   3650.0   0.265663305328</datum>
    <datum>   3651.0   0.265611971516</datum>
    <datum>   3652.0   0.26556046835</datum>
    <datum>   3653.0   0.265508795924</datum>
    <datum>   3654.0   0.265456954334</datum>
    <datum>   3655.0   0.265404943676</datum>
    <datum>   3656.0   0.265352764044</datum>
    <datum>   3657.0   0.265300415534</datum>
    <datum>   3658.0   0.265247898242</datum>
    <datum>   3659.0   0.265195212263</datum>
    <datum>   3660.0   0.265142357693</datum>
    <datum>   3661.0   0.265074998139</datum>
    <datum>   3662.0   0.265007479119</datum>
    <datum>   3663.0   0.264939800736</datum>
    <datum>   3664.0   0.264871963097</datum>
    <datum>   3665.0   0.264803966306</datum>
    <datum>   3666.0   0.264735810468</datum>
    <datum>   3667.0   0.264667495687</datum>
    <datum>   3668.0   0.264599022069</datum>
    <datum>   3669.0   0.264530389718</datum>
    <datum>   3670.0   0.26446159874</datum>
    <datum>   3671.0   0.264544784499</datum>
    <datum>   3672.0   0.264627845497</datum>
    <datum>   3673.0   0.264710781584</datum>
    <datum>   3674.0   0.264793592611</datum>
    <datum>   3675.0   0.264876278428</datum>
    <datum>   3676.0   0.264958838883</datum>
    <datum>   3677.0   0.265041273827</datum>
    <datum>   3678.0   0.26512358311</datum>
    <datum>   3679.0   0.26520576658</datum>
    <datum>   3680.0   0.265287824088</datum>
    <datum>   3681.0   0.265372505644</datum>
    <datum>   3682.0   0.26545705036</datum>
    <datum>   3683.0   0.265541458081</datum>
    <datum>   3684.0   0.265625728656</datum>
    <datum>   3685.0   0.265709861932</datum>
    <datum>   3686.0   0.265793857756</datum>
    <datum>   3687.0   0.265877715975</datum>
    <datum>   3688.0   0.265961436437</datum>
    <datum>   3689.0   0.266045018988</datum>
    <datum>   3690.0   0.266128463477</datum>
    <datum>   3691.0   0.2661672454</datum>
    <datum>   3692.0   0.266205848319</datum>
    <datum>   3693.0   0.266244272082</datum>
    <datum>   3694.0   0.266282516538</datum>
    <datum>   3695.0   0.266320581536</datum>
    <datum>   3696.0   0.266358466924</datum>
    <datum>   3697.0   0.266396172552</datum>
    <datum>   3698.0   0.266433698267</datum>
    <datum>   3699.0   0.266471043918</datum>
    <datum>   3700.0   0.266508209354</datum>
    <datum>   3701.0   0.266853447393</datum>
    <datum>   3702.0   0.267198988691</datum>
    <datum>   3703.0   0.267544833412</datum>
    <datum>   3704.0   0.267890981723</datum>
    <datum>   3705.0   0.268237433791</datum>
    <datum>   3706.0   0.268584189782</datum>
    <datum>   3707.0   0.268931249861</datum>
    <datum>   3708.0   0.269278614196</datum>
    <datum>   3709.0   0.269626282953</datum>
    <datum>   3710.0   0.269974256298</datum>
    <datum>   3711.0   0.270232074236</datum>
    <datum>   3712.0   0.270489995125</datum>
    <datum>   3713.0   0.270748018929</datum>
    <datum>   3714.0   0.27100614561</datum>
    <datum>   3715.0   0.27126437513</datum>
    <datum>   3716.0   0.271522707454</datum>
    <datum>   3717.0   0.271781142543</datum>
    <datum>   3718.0   0.27203968036</datum>
    <datum>   3719.0   0.272298320868</datum>
    <datum>   3720.0   0.272557064029</datum>
    <datum>   3721.0   0.272798346557</datum>
    <datum>   3722.0   0.273039664424</datum>
    <datum>   3723.0   0.273281017499</datum>
    <datum>   3724.0   0.273522405652</datum>
    <datum>   3725.0   0.273763828751</datum>
    <datum>   3726.0   0.274005286667</datum>
    <datum>   3727.0   0.274246779267</datum>
    <datum>   3728.0   0.274488306423</datum>
    <datum>   3729.0   0.274729868001</datum>
    <datum>   3730.0   0.274971463873</datum>
    <datum>   3731.0   0.275241802793</datum>
    <datum>   3732.0   0.275512220461</datum>
    <datum>   3733.0   0.275782716737</datum>
    <datum>   3734.0   0.276053291483</datum>
    <datum>   3735.0   0.276323944559</datum>
    <datum>   3736.0   0.276594675825</datum>
    <datum>   3737.0   0.276865485143</datum>
    <datum>   3738.0   0.277136372372</datum>
    <datum>   3739.0   0.277407337373</datum>
    <datum>   3740.0   0.277678380005</datum>
    <datum>   3741.0   0.27791070157</datum>
    <datum>   3742.0   0.278143073673</datum>
    <datum>   3743.0   0.278375496231</datum>
    <datum>   3744.0   0.278607969161</datum>
    <datum>   3745.0   0.278840492381</datum>
    <datum>   3746.0   0.279073065809</datum>
    <datum>   3747.0   0.279305689362</datum>
    <datum>   3748.0   0.279538362957</datum>
    <datum>   3749.0   0.279771086511</datum>
    <datum>   3750.0   0.280003859941</datum>
    <datum>   3751.0   0.28034180717</datum>
    <datum>   3752.0   0.28068000416</datum>
    <datum>   3753.0   0.281018451002</datum>
    <datum>   3754.0   0.281357147787</datum>
    <datum>   3755.0   0.281696094604</datum>
    <datum>   3756.0   0.282035291545</datum>
    <datum>   3757.0   0.282374738701</datum>
    <datum>   3758.0   0.282714436162</datum>
    <datum>   3759.0   0.283054384018</datum>
    <datum>   3760.0   0.283394582361</datum>
    <datum>   3761.0   0.283772012817</datum>
    <datum>   3762.0   0.284149765777</datum>
    <datum>   3763.0   0.284527841392</datum>
    <datum>   3764.0   0.284906239812</datum>
    <datum>   3765.0   0.285284961189</datum>
    <datum>   3766.0   0.285664005672</datum>
    <datum>   3767.0   0.286043373412</datum>
    <datum>   3768.0   0.28642306456</datum>
    <datum>   3769.0   0.286803079266</datum>
    <datum>   3770.0   0.287183417682</datum>
    <datum>   3771.0   0.287632986917</datum>
    <datum>   3772.0   0.288083046027</datum>
    <datum>   3773.0   0.288533595338</datum>
    <datum>   3774.0   0.288984635174</datum>
    <datum>   3775.0   0.28943616586</datum>
    <datum>   3776.0   0.289888187721</datum>
    <datum>   3777.0   0.290340701084</datum>
    <datum>   3778.0   0.290793706272</datum>
    <datum>   3779.0   0.291247203613</datum>
    <datum>   3780.0   0.291701193431</datum>
    <datum>   3781.0   0.292132073563</datum>
    <datum>   3782.0   0.292563410957</datum>
    <datum>   3783.0   0.29299520595</datum>
    <datum>   3784.0   0.293427458881</datum>
    <datum>   3785.0   0.293860170086</datum>
    <datum>   3786.0   0.294293339904</datum>
    <datum>   3787.0   0.294726968673</datum>
    <datum>   3788.0   0.295161056731</datum>
    <datum>   3789.0   0.295595604415</datum>
    <datum>   3790.0   0.296030612066</datum>
    <datum>   3791.0   0.296331137533</datum>
    <datum>   3792.0   0.296631825651</datum>
    <datum>   3793.0   0.296932676438</datum>
    <datum>   3794.0   0.297233689912</datum>
    <datum>   3795.0   0.297534866091</datum>
    <datum>   3796.0   0.297836204995</datum>
    <datum>   3797.0   0.298137706641</datum>
    <datum>   3798.0   0.298439371047</datum>
    <datum>   3799.0   0.298741198233</datum>
    <datum>   3800.0   0.299043188216</datum>
    <datum>   3801.0   0.299388060359</datum>
    <datum>   3802.0   0.299733202463</datum>
    <datum>   3803.0   0.300078614651</datum>
    <datum>   3804.0   0.300424297053</datum>
    <datum>   3805.0   0.300770249792</datum>
    <datum>   3806.0   0.301116472996</datum>
    <datum>   3807.0   0.301462966791</datum>
    <datum>   3808.0   0.301809731303</datum>
    <datum>   3809.0   0.302156766659</datum>
    <datum>   3810.0   0.302504072985</datum>
    <datum>   3811.0   0.302290239284</datum>
    <datum>   3812.0   0.302075541713</datum>
    <datum>   3813.0   0.301859979379</datum>
    <datum>   3814.0   0.301643551385</datum>
    <datum>   3815.0   0.301426256834</datum>
    <datum>   3816.0   0.301208094832</datum>
    <datum>   3817.0   0.300989064482</datum>
    <datum>   3818.0   0.300769164886</datum>
    <datum>   3819.0   0.300548395148</datum>
    <datum>   3820.0   0.30032675437</datum>
    <datum>   3821.0   0.298793383699</datum>
    <datum>   3822.0   0.297256483876</datum>
    <datum>   3823.0   0.295716051631</datum>
    <datum>   3824.0   0.294172083691</datum>
    <datum>   3825.0   0.292624576784</datum>
    <datum>   3826.0   0.291073527634</datum>
    <datum>   3827.0   0.289518932967</datum>
    <datum>   3828.0   0.287960789507</datum>
    <datum>   3829.0   0.286399093976</datum>
    <datum>   3830.0   0.284833843095</datum>
    <datum>   3831.0   0.283596382078</datum>
    <datum>   3832.0   0.282355702811</datum>
    <datum>   3833.0   0.281111801548</datum>
    <datum>   3834.0   0.279864674539</datum>
    <datum>   3835.0   0.278614318035</datum>
    <datum>   3836.0   0.277360728281</datum>
    <datum>   3837.0   0.276103901523</datum>
    <datum>   3838.0   0.274843834003</datum>
    <datum>   3839.0   0.273580521959</datum>
    <datum>   3840.0   0.272313961631</datum>
    <datum>   3841.0   0.270790707716</datum>
    <datum>   3842.0   0.269264228475</datum>
    <datum>   3843.0   0.267734521149</datum>
    <datum>   3844.0   0.266201582976</datum>
    <datum>   3845.0   0.264665411193</datum>
    <datum>   3846.0   0.263126003038</datum>
    <datum>   3847.0   0.261583355746</datum>
    <datum>   3848.0   0.260037466554</datum>
    <datum>   3849.0   0.258488332695</datum>
    <datum>   3850.0   0.256935951404</datum>
    <datum>   3851.0   0.255390630498</datum>
    <datum>   3852.0   0.253841706237</datum>
    <datum>   3853.0   0.252289175325</datum>
    <datum>   3854.0   0.250733034463</datum>
    <datum>   3855.0   0.249173280353</datum>
    <datum>   3856.0   0.247609909696</datum>
    <datum>   3857.0   0.246042919189</datum>
    <datum>   3858.0   0.244472305532</datum>
    <datum>   3859.0   0.242898065423</datum>
    <datum>   3860.0   0.241320195557</datum>
    <datum>   3861.0   0.240086672498</datum>
    <datum>   3862.0   0.238850257122</datum>
    <datum>   3863.0   0.237610946857</datum>
    <datum>   3864.0   0.23636873913</datum>
    <datum>   3865.0   0.235123631371</datum>
    <datum>   3866.0   0.233875621004</datum>
    <datum>   3867.0   0.232624705455</datum>
    <datum>   3868.0   0.231370882151</datum>
    <datum>   3869.0   0.230114148515</datum>
    <datum>   3870.0   0.228854501972</datum>
    <datum>   3871.0   0.228212939992</datum>
    <datum>   3872.0   0.227569698363</datum>
    <datum>   3873.0   0.226924775574</datum>
    <datum>   3874.0   0.226278170113</datum>
    <datum>   3875.0   0.225629880468</datum>
    <datum>   3876.0   0.224979905126</datum>
    <datum>   3877.0   0.224328242575</datum>
    <datum>   3878.0   0.223674891301</datum>
    <datum>   3879.0   0.223019849791</datum>
    <datum>   3880.0   0.222363116531</datum>
    <datum>   3881.0   0.221970005696</datum>
    <datum>   3882.0   0.221575686508</datum>
    <datum>   3883.0   0.221180157856</datum>
    <datum>   3884.0   0.220783418627</datum>
    <datum>   3885.0   0.220385467711</datum>
    <datum>   3886.0   0.219986303995</datum>
    <datum>   3887.0   0.219585926366</datum>
    <datum>   3888.0   0.219184333712</datum>
    <datum>   3889.0   0.218781524921</datum>
    <datum>   3890.0   0.218377498878</datum>
    <datum>   3891.0   0.217267347027</datum>
    <datum>   3892.0   0.2161544669</datum>
    <datum>   3893.0   0.215038855549</datum>
    <datum>   3894.0   0.213920510026</datum>
    <datum>   3895.0   0.21279942738</datum>
    <datum>   3896.0   0.211675604659</datum>
    <datum>   3897.0   0.210549038912</datum>
    <datum>   3898.0   0.209419727182</datum>
    <datum>   3899.0   0.208287666513</datum>
    <datum>   3900.0   0.207152853947</datum>
    <datum>   3901.0   0.204733542233</datum>
    <datum>   3902.0   0.202308731268</datum>
    <datum>   3903.0   0.199878416474</datum>
    <datum>   3904.0   0.197442593272</datum>
    <datum>   3905.0   0.195001257081</datum>
    <datum>   3906.0   0.19255440332</datum>
    <datum>   3907.0   0.190102027406</datum>
    <datum>   3908.0   0.187644124757</datum>
    <datum>   3909.0   0.185180690788</datum>
    <datum>   3910.0   0.182711720915</datum>
    <datum>   3911.0   0.179532289265</datum>
    <datum>   3912.0   0.176346023353</datum>
    <datum>   3913.0   0.173152917766</datum>
    <datum>   3914.0   0.169952967091</datum>
    <datum>   3915.0   0.166746165914</datum>
    <datum>   3916.0   0.16353250882</datum>
    <datum>   3917.0   0.160311990394</datum>
    <datum>   3918.0   0.157084605219</datum>
    <datum>   3919.0   0.153850347878</datum>
    <datum>   3920.0   0.150609212951</datum>
    <datum>   3921.0   0.147620223727</datum>
    <datum>   3922.0   0.144625698474</datum>
    <datum>   3923.0   0.141625633163</datum>
    <datum>   3924.0   0.138620023767</datum>
    <datum>   3925.0   0.135608866259</datum>
    <datum>   3926.0   0.132592156609</datum>
    <datum>   3927.0   0.129569890787</datum>
    <datum>   3928.0   0.126542064766</datum>
    <datum>   3929.0   0.123508674513</datum>
    <datum>   3930.0   0.120469715998</datum>
    <datum>   3931.0   0.118238261105</datum>
    <datum>   3932.0   0.116001825112</datum>
    <datum>   3933.0   0.113760404117</datum>
    <datum>   3934.0   0.11151399422</datum>
    <datum>   3935.0   0.109262591519</datum>
    <datum>   3936.0   0.107006192113</datum>
    <datum>   3937.0   0.104744792099</datum>
    <datum>   3938.0   0.102478387576</datum>
    <datum>   3939.0   0.100206974639</datum>
    <datum>   3940.0   0.0979305493866</datum>
    <datum>   3941.0   0.0964690004011</datum>
    <datum>   3942.0   0.095003909804</datum>
    <datum>   3943.0   0.0935352740265</datum>
    <datum>   3944.0   0.0920630894987</datum>
    <datum>   3945.0   0.0905873526486</datum>
    <datum>   3946.0   0.0891080599029</datum>
    <datum>   3947.0   0.0876252076865</datum>
    <datum>   3948.0   0.0861387924228</datum>
    <datum>   3949.0   0.0846488105336</datum>
    <datum>   3950.0   0.0831552584391</datum>
    <datum>   3951.0   0.082236643117</datum>
    <datum>   3952.0   0.0813159912506</datum>
    <datum>   3953.0   0.0803933013691</datum>
    <datum>   3954.0   0.0794685720015</datum>
    <datum>   3955.0   0.0785418016767</datum>
    <datum>   3956.0   0.0776129889236</datum>
    <datum>   3957.0   0.0766821322708</datum>
    <datum>   3958.0   0.0757492302471</datum>
    <datum>   3959.0   0.0748142813811</datum>
    <datum>   3960.0   0.0738772842013</datum>
    <datum>   3961.0   0.0731890670643</datum>
    <datum>   3962.0   0.0724992682497</datum>
    <datum>   3963.0   0.0718078865802</datum>
    <datum>   3964.0   0.0711149208789</datum>
    <datum>   3965.0   0.0704203699686</datum>
    <datum>   3966.0   0.0697242326722</datum>
    <datum>   3967.0   0.0690265078124</datum>
    <datum>   3968.0   0.068327194212</datum>
    <datum>   3969.0   0.0676262906939</datum>
    <datum>   3970.0   0.0669237960806</datum>
    <datum>   3971.0   0.0661106100153</datum>
    <datum>   3972.0   0.0652957208114</datum>
    <datum>   3973.0   0.0644791274008</datum>
    <datum>   3974.0   0.0636608287155</datum>
    <datum>   3975.0   0.0628408236873</datum>
    <datum>   3976.0   0.0620191112481</datum>
    <datum>   3977.0   0.06119569033</datum>
    <datum>   3978.0   0.0603705598648</datum>
    <datum>   3979.0   0.0595437187844</datum>
    <datum>   3980.0   0.0587151660208</datum>
    <datum>   3981.0   0.0576545426141</datum>
    <datum>   3982.0   0.05659162989</datum>
    <datum>   3983.0   0.0555264262821</datum>
    <datum>   3984.0   0.0544589302244</datum>
    <datum>   3985.0   0.0533891401509</datum>
    <datum>   3986.0   0.0523170544954</datum>
    <datum>   3987.0   0.0512426716922</datum>
    <datum>   3988.0   0.0501659901752</datum>
    <datum>   3989.0   0.0490870083786</datum>
    <datum>   3990.0   0.0480057247367</datum>
    <datum>   3991.0   0.0468883235124</datum>
    <datum>   3992.0   0.045768736881</datum>
    <datum>   3993.0   0.0446469635697</datum>
    <datum>   3994.0   0.0435230023056</datum>
    <datum>   3995.0   0.0423968518163</datum>
    <datum>   3996.0   0.0412685108291</datum>
    <datum>   3997.0   0.0401379780716</datum>
    <datum>   3998.0   0.0390052522714</datum>
    <datum>   3999.0   0.037870332156</datum>
    <datum>   4000.0   0.0367332164535</datum>
    <datum>   4001.0   0.0358352895939</datum>
    <datum>   4002.0   0.0349356153999</datum>
    <datum>   4003.0   0.0340341928122</datum>
    <datum>   4004.0   0.0331310207714</datum>
    <datum>   4005.0   0.0322260982184</datum>
    <datum>   4006.0   0.0313194240942</datum>
    <datum>   4007.0   0.0304109973398</datum>
    <datum>   4008.0   0.0295008168964</datum>
    <datum>   4009.0   0.028588881705</datum>
    <datum>   4010.0   0.0276751907073</datum>
    <datum>   4011.0   0.0270800549977</datum>
    <datum>   4012.0   0.0264837324587</datum>
    <datum>   4013.0   0.0258862223488</datum>
    <datum>   4014.0   0.0252875239266</datum>
    <datum>   4015.0   0.0246876364508</datum>
    <datum>   4016.0   0.0240865591801</datum>
    <datum>   4017.0   0.0234842913734</datum>
    <datum>   4018.0   0.0228808322896</datum>
    <datum>   4019.0   0.0222761811879</datum>
    <datum>   4020.0   0.0216703373273</datum>
    <datum>   4021.0   0.021322436645</datum>
    <datum>   4022.0   0.020973760841</datum>
    <datum>   4023.0   0.0206243092455</datum>
    <datum>   4024.0   0.0202740811882</datum>
    <datum>   4025.0   0.0199230759991</datum>
    <datum>   4026.0   0.0195712930075</datum>
    <datum>   4027.0   0.019218731543</datum>
    <datum>   4028.0   0.0188653909347</datum>
    <datum>   4029.0   0.0185112705115</datum>
    <datum>   4030.0   0.0181563696025</datum>
    <datum>   4031.0   0.0179567527583</datum>
    <datum>   4032.0   0.0177567618138</datum>
    <datum>   4033.0   0.0175563965826</datum>
    <datum>   4034.0   0.0173556568782</datum>
    <datum>   4035.0   0.0171545425144</datum>
    <datum>   4036.0   0.0169530533047</datum>
    <datum>   4037.0   0.016751189063</datum>
    <datum>   4038.0   0.0165489496028</datum>
    <datum>   4039.0   0.016346334738</datum>
    <datum>   4040.0   0.0161433442823</datum>
    <datum>   4041.0   0.0159949730275</datum>
    <datum>   4042.0   0.0158463299104</datum>
    <datum>   4043.0   0.0156974148021</datum>
    <datum>   4044.0   0.0155482275732</datum>
    <datum>   4045.0   0.0153987680947</datum>
    <datum>   4046.0   0.0152490362373</datum>
    <datum>   4047.0   0.0150990318721</datum>
    <datum>   4048.0   0.01494875487</datum>
    <datum>   4049.0   0.0147982051018</datum>
    <datum>   4050.0   0.0146473824388</datum>
    <datum>   4051.0   0.0144514597296</datum>
    <datum>   4052.0   0.0142551541437</datum>
    <datum>   4053.0   0.0140584654708</datum>
    <datum>   4054.0   0.0138613935007</datum>
    <datum>   4055.0   0.0136639380235</datum>
    <datum>   4056.0   0.013466098829</datum>
    <datum>   4057.0   0.0132678757074</datum>
    <datum>   4058.0   0.0130692684486</datum>
    <datum>   4059.0   0.0128702768428</datum>
    <datum>   4060.0   0.0126709006802</datum>
    <datum>   4061.0   0.0124038899475</datum>
    <datum>   4062.0   0.0121363783644</datum>
    <datum>   4063.0   0.0118683656742</datum>
    <datum>   4064.0   0.0115998516204</datum>
    <datum>   4065.0   0.0113308359466</datum>
    <datum>   4066.0   0.0110613183964</datum>
    <datum>   4067.0   0.0107912987135</datum>
    <datum>   4068.0   0.0105207766418</datum>
    <datum>   4069.0   0.010249751925</datum>
    <datum>   4070.0   0.00997822430725</datum>
    <datum>   4071.0   0.0097265028936</datum>
    <datum>   4072.0   0.00947436855394</datum>
    <datum>   4073.0   0.00922182114797</datum>
    <datum>   4074.0   0.00896886053544</datum>
    <datum>   4075.0   0.00871548657615</datum>
    <datum>   4076.0   0.00846169912994</datum>
    <datum>   4077.0   0.00820749805672</datum>
    <datum>   4078.0   0.00795288321644</datum>
    <datum>   4079.0   0.0076978544691</datum>
    <datum>   4080.0   0.00744241167477</datum>
    <datum>   4081.0   0.00727599443781</datum>
    <datum>   4082.0   0.00710928822155</datum>
    <datum>   4083.0   0.00694229290691</datum>
    <datum>   4084.0   0.00677500837486</datum>
    <datum>   4085.0   0.00660743450641</datum>
    <datum>   4086.0   0.00643957118263</datum>
    <datum>   4087.0   0.00627141828461</datum>
    <datum>   4088.0   0.0061029756935</datum>
    <datum>   4089.0   0.00593424329049</datum>
    <datum>   4090.0   0.00576522095682</datum>
    <datum>   4091.0   0.00567825781708</datum>
    <datum>   4092.0   0.00559114275833</datum>
    <datum>   4093.0   0.00550387571593</datum>
    <datum>   4094.0   0.00541645662528</datum>
    <datum>   4095.0   0.00532888542179</datum>
    <datum>   4096.0   0.00524116204089</datum>
    <datum>   4097.0   0.00515328641806</datum>
    <datum>   4098.0   0.00506525848877</datum>
    <datum>   4099.0   0.00497707818855</datum>
    <datum>   4100.0   0.00488874545294</datum>
    <datum>   4101.0   0.00484268791073</datum>
    <datum>   4102.0   0.00479658001642</datum>
    <datum>   4103.0   0.00475042175651</datum>
    <datum>   4104.0   0.00470421311753</datum>
    <datum>   4105.0   0.004657954086</datum>
    <datum>   4106.0   0.00461164464847</datum>
    <datum>   4107.0   0.00456528479148</datum>
    <datum>   4108.0   0.00451887450157</datum>
    <datum>   4109.0   0.00447241376531</datum>
    <datum>   4110.0   0.00442590256926</datum>
    <datum>   4111.0   0.0043881379806</datum>
    <datum>   4112.0   0.00435033077365</datum>
    <datum>   4113.0   0.00431248093676</datum>
    <datum>   4114.0   0.00427458845829</datum>
    <datum>   4115.0   0.00423665332661</datum>
    <datum>   4116.0   0.0041986755301</datum>
    <datum>   4117.0   0.00416065505713</datum>
    <datum>   4118.0   0.0041225918961</datum>
    <datum>   4119.0   0.00408448603539</datum>
    <datum>   4120.0   0.0040463374634</datum>
    <datum>   4121.0   0.00400702556375</datum>
    <datum>   4122.0   0.00396767867648</datum>
    <datum>   4123.0   0.00392829679553</datum>
    <datum>   4124.0   0.00388887991489</datum>
    <datum>   4125.0   0.00384942802853</datum>
    <datum>   4126.0   0.00380994113042</datum>
    <datum>   4127.0   0.00377041921455</datum>
    <datum>   4128.0   0.00373086227491</datum>
    <datum>   4129.0   0.00369127030547</datum>
    <datum>   4130.0   0.00365164330025</datum>
    <datum>   4131.0   0.00362253596465</datum>
    <datum>   4132.0   0.00359339804738</datum>
    <datum>   4133.0   0.00356422954132</datum>
    <datum>   4134.0   0.0035350304394</datum>
    <datum>   4135.0   0.00350580073452</datum>
    <datum>   4136.0   0.0034765404196</datum>
    <datum>   4137.0   0.00344724948756</datum>
    <datum>   4138.0   0.00341792793133</datum>
    <datum>   4139.0   0.00338857574383</datum>
    <datum>   4140.0   0.00335919291801</datum>
    <datum>   4141.0   0.00335090552158</datum>
    <datum>   4142.0   0.00334260836228</datum>
    <datum>   4143.0   0.00333430143769</datum>
    <datum>   4144.0   0.00332598474542</datum>
    <datum>   4145.0   0.00331765828307</datum>
    <datum>   4146.0   0.00330932204825</datum>
    <datum>   4147.0   0.00330097603854</datum>
    <datum>   4148.0   0.00329262025156</datum>
    <datum>   4149.0   0.00328425468492</datum>
    <datum>   4150.0   0.00327587933618</datum>
    <datum>   4151.0   0.00315628445906</datum>
    <datum>   4152.0   0.00303656663852</datum>
    <datum>   4153.0   0.00291672584648</datum>
    <datum>   4154.0   0.00279676205485</datum>
    <datum>   4155.0   0.00267667523557</datum>
    <datum>   4156.0   0.0025564653606</datum>
    <datum>   4157.0   0.00243613240192</datum>
    <datum>   4158.0   0.00231567633152</datum>
    <datum>   4159.0   0.00219509712143</datum>
    <datum>   4160.0   0.00207439474367</datum>
    <datum>   4161.0   0.00200176289934</datum>
    <datum>   4162.0   0.00192906379257</datum>
    <datum>   4163.0   0.00185629741089</datum>
    <datum>   4164.0   0.00178346374183</datum>
    <datum>   4165.0   0.00171056277292</datum>
    <datum>   4166.0   0.00163759449171</datum>
    <datum>   4167.0   0.00156455888576</datum>
    <datum>   4168.0   0.00149145594262</datum>
    <datum>   4169.0   0.00141828564988</datum>
    <datum>   4170.0   0.00134504799512</datum>
    <datum>   4171.0   0.00130094913431</datum>
    <datum>   4172.0   0.00125681130256</datum>
    <datum>   4173.0   0.00121263449344</datum>
    <datum>   4174.0   0.0011684187005</datum>
    <datum>   4175.0   0.0011241639173</datum>
    <datum>   4176.0   0.0010798701374</datum>
    <datum>   4177.0   0.00103553735438</datum>
    <datum>   4178.0   0.000991165561799</datum>
    <datum>   4179.0   0.000946754753246</datum>
    <datum>   4180.0   0.00090230492231</datum>
    <datum>   4181.0   0.000874657674313</datum>
    <datum>   4182.0   0.000846985346779</datum>
    <datum>   4183.0   0.000819287935405</datum>
    <datum>   4184.0   0.000791565435891</datum>
    <datum>   4185.0   0.000763817843939</datum>
    <datum>   4186.0   0.000736045155256</datum>
    <datum>   4187.0   0.000708247365553</datum>
    <datum>   4188.0   0.000680424470542</datum>
    <datum>   4189.0   0.000652576465941</datum>
    <datum>   4190.0   0.000624703347473</datum>
    <datum>   4191.0   0.000606863756592</datum>
    <datum>   4192.0   0.000589004502188</datum>
    <datum>   4193.0   0.000571125575711</datum>
    <datum>   4194.0   0.000553226968612</datum>
    <datum>   4195.0   0.000535308672341</datum>
    <datum>   4196.0   0.000517370678349</datum>
    <datum>   4197.0   0.000499412978086</datum>
    <datum>   4198.0   0.000481435563001</datum>
    <datum>   4199.0   0.000463438424545</datum>
    <datum>   4200.0   0.00044542155417</datum>
    <datum>   4201.0   0.000433506962611</datum>
    <datum>   4202.0   0.000421579983458</datum>
    <datum>   4203.0   0.000409640614146</datum>
    <datum>   4204.0   0.000397688852116</datum>
    <datum>   4205.0   0.000385724694807</datum>
    <datum>   4206.0   0.000373748139662</datum>
    <datum>   4207.0   0.000361759184126</datum>
    <datum>   4208.0   0.000349757825645</datum>
    <datum>   4209.0   0.000337744061669</datum>
    <datum>   4210.0   0.000325717889647</datum>
    <datum>   4211.0   0.000317533138448</datum>
    <datum>   4212.0   0.000309339914647</datum>
    <datum>   4213.0   0.000301138216469</datum>
    <datum>   4214.0   0.000292928042138</datum>
    <datum>   4215.0   0.000284709389881</datum>
    <datum>   4216.0   0.000276482257926</datum>
    <datum>   4217.0   0.000268246644502</datum>
    <datum>   4218.0   0.000260002547838</datum>
    <datum>   4219.0   0.000251749966165</datum>
    <datum>   4220.0   0.000243488897718</datum>
    <datum>   4221.0   0.000237757105973</datum>
    <datum>   4222.0   0.000232019478466</datum>
    <datum>   4223.0   0.000226276014043</datum>
    <datum>   4224.0   0.00022052671155</datum>
    <datum>   4225.0   0.000214771569833</datum>
    <datum>   4226.0   0.000209010587742</datum>
    <datum>   4227.0   0.000203243764124</datum>
    <datum>   4228.0   0.00019747109783</datum>
    <datum>   4229.0   0.000191692587709</datum>
    <datum>   4230.0   0.000185908232615</datum>
    <datum>   4231.0   0.000181841687888</datum>
    <datum>   4232.0   0.000177771317164</datum>
    <datum>   4233.0   0.000173697119826</datum>
    <datum>   4234.0   0.000169619095257</datum>
    <datum>   4235.0   0.000165537242841</datum>
    <datum>   4236.0   0.000161451561961</datum>
    <datum>   4237.0   0.000157362052003</datum>
    <datum>   4238.0   0.000153268712352</datum>
    <datum>   4239.0   0.000149171542393</datum>
    <datum>   4240.0   0.000145070541512</datum>
    <datum>   4241.0   0.000142056721273</datum>
    <datum>   4242.0   0.000139039869051</datum>
    <datum>   4243.0   0.000136019984219</datum>
    <datum>   4244.0   0.00013299706615</datum>
    <datum>   4245.0   0.000129971114219</datum>
    <datum>   4246.0   0.0001269421278</datum>
    <datum>   4247.0   0.000123910106268</datum>
    <datum>   4248.0   0.000120875048999</datum>
    <datum>   4249.0   0.000117836955369</datum>
    <datum>   4250.0   0.000114795824754</datum>
    <datum>   4251.0   0.000112544972726</datum>
    <datum>   4252.0   0.000110291559836</datum>
    <datum>   4253.0   0.000108035585391</datum>
    <datum>   4254.0   0.000105777048698</datum>
    <datum>   4255.0   0.000103515949062</datum>
    <datum>   4256.0   0.000101252285792</datum>
  </response>
  <effectiveWavelength>3589.14671839839</effectiveWavelength>
  <vegaOffset>-0.799601880942569</vegaOffset>
</filter>
